picdb/__init__.py
picdb/api.py
picdb/cli.py
py_picdb-0.1.0.dist-info/LICENSE
py_picdb-0.1.0.dist-info/METADATA
py_picdb-0.1.0.dist-info/WHEEL
py_picdb-0.1.0.dist-info/entry_points.txt
py_picdb-0.1.0.dist-info/top_level.txt
py_picdb-0.1.0.dist-info/RECORD
