Metadata-Version: 2.1
Name: py-picdb
Version: 0.1.0
Summary: Command-line tool and library for PicDB API, which provides storage for images.
Home-page: https://github.com/AkkilMG/PicDB-Python
Author: Akkil MG
Author-email: akkilcharanmg@gmail.com
Classifier: Programming Language :: Python :: 3
Classifier: License :: OSI Approved :: MIT License
Classifier: Operating System :: OS Independent
Requires-Python: >=3.6
License-File: LICENSE
Requires-Dist: requests
